MANIFEST.in
README.md
requirements.txt
setup.cfg
setup.py
ENPC_Aligner.egg-info/PKG-INFO
ENPC_Aligner.egg-info/SOURCES.txt
ENPC_Aligner.egg-info/dependency_links.txt
ENPC_Aligner.egg-info/not-zip-safe
ENPC_Aligner.egg-info/requires.txt
ENPC_Aligner.egg-info/top_level.txt
bin/align-example
enpc_aligner/IBM1_func.py
enpc_aligner/IBM2_func.py
enpc_aligner/__init__.py
enpc_aligner/dtw.py
enpc_aligner/version.py
enpc_aligner/words_correspondence.py
examples/example.py
examples/reformat.py
examples/english/UN.txt
examples/english/bible.txt
examples/english/le-petit-prince--antoine-de-saint-exupery.txt
examples/english/pinocchio.txt
examples/french/LOiseau-bleu.txt
examples/french/Le-Tour-du-monde-en-quatre-vingts-jours.txt
examples/french/UN.txt
examples/french/bible.txt
examples/french/le-petit-prince--antoine-de-saint-exupery.txt
examples/french/pinocchio.txt
examples/russian/LOiseau-bleu.txt
examples/russian/Le-Tour-du-monde-en-quatre-vingts-jours.txt
examples/russian/UN.txt