Metadata-Version: 1.0
Name: ENPC-Aligner
Version: 1.0.5
Summary: Library of alignment of translated texts in differents languages
Home-page: https://github.com/PhilippeFerreiraDeSousa/bitext-matching
Author: Philippe Ferreira De Sousa
Author-email: philippe@fdesousa.fr
License: MIT
Keywords: alignment bitext ibm dtw
Platform: UNKNOWN
